{"type":"FeatureCollection","features":[{"geometry": {"type": "Point", "coordinates": [-117.41480482899999, 33.24338697200005]}, "type": "Feature", "id": 1, "properties": {"RailYard_ID_1": 1, "SvcName2": 4, "OBJECTID_1": 3, "SvcName1": 3, "Operator1": 2, "SvcName3": 8, "Operator2": 4, "RailYard_ID": 1, "RailYard_Name": "Oceanside", "SvcType2": 2, "SvcType3": 4, "SvcType1": 1, "RAILYARD_NAME_1": "Oceanside", "Owner": 1, "InSD": 1, "TrackType": 1, "Operator3": 5, "MILEAGE": 0.6859594504264068}},{"geometry": {"type": "Point", "coordinates": [-117.16505455899994, 32.87842703300004]}, "type": "Feature", "id": 2, "properties": {"RailYard_ID_1": 2, "RailYard_ID": 2, "OBJECTID_1": 4, "SvcName1": 8, "Operator2": 11, "SvcName2": 9, "RailYard_Name": "Miramar", "SvcType2": 4, "Operator1": 5, "SvcType1": 4, "RAILYARD_NAME_1": "Miramar Road", "Owner": 5, "InSD": 1, "TrackType": 5, "MILEAGE": 0.04809069364678226}},{"geometry": {"type": "Point", "coordinates": [-117.15257828999995, 32.70012449800004]}, "type": "Feature", "id": 3, "properties": {"RailYard_ID_1": 3, "MILEAGE": 0.027559862089570408, "OBJECTID_1": 1, "SvcName1": 8, "RailYard_ID": 3, "RailYard_Name": "Tenth Avenue", "Operator1": 5, "SvcType1": 4, "RAILYARD_NAME_1": "Tenth Avenue", "Owner": 5, "InSD": 1, "TrackType": 5}},{"geometry": {"type": "Point", "coordinates": [-117.03271505299995, 32.54866606400003]}, "type": "Feature", "id": 4, "properties": {"RailYard_ID_1": 4, "MILEAGE": 0.06892445978516168, "OBJECTID_1": 2, "SvcName1": 8, "RailYard_ID": 4, "RailYard_Name": "San Ysidro", "Operator1": 6, "SvcType1": 4, "RAILYARD_NAME_1": "San Ysidro", "Owner": 4, "InSD": 1, "TrackType": 1}}]}